ChangeLog
INSTALL
LICENSE
README
TODO
VERSION
ez_setup.py
setup.py
NetCIDR.egg-info/PKG-INFO
NetCIDR.egg-info/SOURCES.txt
NetCIDR.egg-info/dependency_links.txt
NetCIDR.egg-info/top_level.txt
admin/clean.sh
admin/commit.sh
admin/rsync_website.sh
admin/stat.sh
netcidr/__init__.py
netcidr/blocks.py
netcidr/ipmath.py
netcidr/networks.py
netcidr/utils.py
tests/test_all.py
